{"63852702":{"data":{"登記機關":"雲林縣政府","核准設立日期":{"year":1962,"month":8,"day":2},"最近異動日期":{"year":1984,"month":4,"day":13},"商業名稱":"新發號","負責人姓名":"陳新","現況":"核准設立","資本額(元)":"8,000","組織類型":"獨資","地址":"雲林縣水林鄉西井村西井路四０號","營業項目":"食品（糖、油、粉、飲料）買賣批發"}},"63853701":{"data":{"登記機關":"雲林縣政府","核准設立日期":{"year":1968,"month":5,"day":21},"最近異動日期":{"year":2007,"month":4,"day":14},"商業名稱":"新勝商號","負責人姓名":"李鄭阿娥","現況":"核准設立","資本額(元)":"5,000","組織類型":"獨資","地址":"雲林縣北港鎮府番里府番路三八號","營業項目":"1\r\n\r\n                    F203020\r\n\r\n                    菸酒零售業\r\n\r\n              \r\n                    2\r\n\r\n                    F399990\r\n\r\n                    其他綜合零售業"}},"63855200":{"data":{"登記機關":"雲林縣政府","核准設立日期":{"year":1965,"month":9,"day":25},"最近異動日期":{"year":2006,"month":3,"day":17},"商業名稱":"源發旅社","負責人姓名":"陳景豐","現況":"核准設立","資本額(元)":"5,000","組織類型":"合夥","地址":"雲林縣北港鎮共榮里民主路三０號","營業項目":"設場屋以集客之業（旅社）","合夥人姓名":"陳榮貴"}},"63855406":{"error":true,"message":"Company not found"},"63855709":{"data":{"登記機關":"雲林縣政府","核准設立日期":{"year":1960,"month":7,"day":1},"最近異動日期":{"year":1995,"month":8,"day":2},"商業名稱":"瑞發商號","負責人姓名":"張成吉","現況":"核准設立","資本額(元)":"36,000","組織類型":"獨資","地址":"雲林縣北港鎮東陽里中山路六０號","營業項目":"木炭、粉類、什糧買賣、麵粉、麩皮、豆類、黃豆洗潔粉、黃豆沙拉油等買賣。"}},"63855905":{"data":{"登記機關":"雲林縣政府","核准設立日期":{"year":1954,"month":12,"day":25},"最近異動日期":{"year":2008,"month":7,"day":15},"商業名稱":"新順發","負責人姓名":"張事夏","現況":"核准設立","資本額(元)":"5,000","組織類型":"獨資","地址":"雲林縣北港鎮扶朝里北港扶朝里扶朝五一號","營業項目":"什貨買賣"}},"63857707":{"error":true,"message":"Company not found"},"63858403":{"data":{"登記機關":"雲林縣政府","核准設立日期":{"year":1965,"month":12,"day":11},"最近異動日期":{"year":2001,"month":6,"day":6},"商業名稱":"裕發碾米工廠","負責人姓名":"呂裕發","現況":"核准設立","資本額(元)":"2,000,000","組織類型":"獨資","地址":"雲林縣水林鄉萡埔村瓊埔路八一之二號","營業項目":"1\r\n\r\n                    A102061\r\n\r\n                    糧商業"}}}